wordavl/__init__.py
wordavl/structures/__init__.py
wordavl/structures/avl.py
wordavl/structures/bst.py
wordavl/text_data.py
wordavl-0.1.0.dist-info/METADATA
wordavl-0.1.0.dist-info/WHEEL
wordavl-0.1.0.dist-info/RECORD
