Metadata-Version: 2.1
Name: wordavl
Version: 0.1.0
Summary: An autocomplete/recommendation system implemented using an AVL datastructure
Author: João Cabral
Author-email: jpfcabral@gmail.com
Requires-Python: >=3.11,<4.0
Classifier: Programming Language :: Python :: 3
Classifier: Programming Language :: Python :: 3.11
Requires-Dist: loguru (>=0.7.2,<0.8.0)
Requires-Dist: requests (>=2.31.0,<3.0.0)
